[{"i":"2778067","n":"Graz","c":[47.06667,15.45],"p":"AT"},{"i":"3462089","n":"Gravatai","c":[-29.94218,-50.99278],"p":"BR"},{"i":"2517117","n":"Granada","c":[37.18817,-3.60667],"p":"ES"},{"i":"4994358","n":"Grand Rapids","c":[42.96336,-85.66809],"p":"US"},{"i":"4694482","n":"Grand Prairie","c":[32.74596,-96.99778],"p":"US"},{"i":"3121245","n":"Gracia","c":[41.40237,2.15641],"p":"ES"},{"i":"5119167","n":"Gravesend","c":[40.5976,-73.96514],"p":"US"},{"i":"2288115","n":"Grand-Bassam","c":[5.2118,-3.73884],"p":"CI"},{"i":"1000501","n":"Grahamstown","c":[-33.30422,26.53276],"p":"ZA"},{"i":"2648182","n":"Grays","c":[51.47566,0.32521],"p":"GB"},{"i":"3619136","n":"Granada","c":[11.92988,-85.95602],"p":"NI"},{"i":"559029","n":"Grazhdanka","c":[60.017,30.417],"p":"RU"},{"i":"5964215","n":"Granby","c":[45.40008,-72.73243],"p":"CA"},{"i":"1000543","n":"Graaff Reinet","c":[-32.25215,24.53075],"p":"ZA"},{"i":"2567529","n":"Grao de Murviedro","c":[39.64167,-0.23889],"p":"ES"},{"i":"3398691","n":"Gravata","c":[-8.20111,-35.56472],"p":"BR"},{"i":"3121145","n":"Granollers","c":[41.60797,2.28773],"p":"ES"},{"i":"5423573","n":"Grand Junction","c":[39.06387,-108.55065],"p":"US"},{"i":"5059429","n":"Grand Forks","c":[47.92526,-97.03285],"p":"US"},{"i":"2648187","n":"Gravesend","c":[51.44206,0.37106],"p":"GB"},{"i":"5069297","n":"Grand Island","c":[40.92501,-98.34201],"p":"US"},{"i":"4694568","n":"Grapevine","c":[32.93429,-97.07807],"p":"US"}]