[{"i":"3395981","n":"Maceio","c":[-9.66583,-35.73528],"p":"BR"},{"i":"1821274","n":"Macau","c":[22.20056,113.54611],"p":"MO"},{"i":"3396016","n":"Macapa","c":[0.03889,-51.06639],"p":"BR"},{"i":"1857871","n":"Machida","c":[35.54028,139.45083],"p":"JP"},{"i":"3654533","n":"Machala","c":[-3.25861,-79.96053],"p":"EC"},{"i":"1264637","n":"Machilipatnam","c":[16.18747,81.13888],"p":"IN"},{"i":"3458266","n":"Macae","c":[-22.38484,-41.78324],"p":"BR"},{"i":"1801582","n":"Macheng","c":[31.18013,115.02213],"p":"CN"},{"i":"2159220","n":"Mackay","c":[-21.15345,149.16554],"p":"AU"},{"i":"4207400","n":"Macon","c":[32.84069,-83.6324],"p":"US"},{"i":"3633444","n":"Machiques","c":[10.06077,-72.55212],"p":"VE"},{"i":"2417988","n":"Macenta","c":[8.54351,-9.47099],"p":"GN"},{"i":"2643266","n":"Macclesfield","c":[53.26023,-2.12564],"p":"GB"},{"i":"188492","n":"Machakos","c":[-1.52233,37.26521],"p":"KE"},{"i":"1264647","n":"Macherla","c":[16.47635,79.43533],"p":"IN"}]