[{"i":"1260086","n":"Patna","c":[25.59408,85.13563],"p":"IN"},{"i":"1260107","n":"Patiala","c":[30.33625,76.3922],"p":"IN"},{"i":"1282931","n":"Patan","c":[27.67658,85.31417],"p":"NP"},{"i":"1328421","n":"Pathein","c":[16.77919,94.73212],"p":"MM"},{"i":"1260137","n":"Pathankot","c":[32.27484,75.65287],"p":"IN"},{"i":"255683","n":"Patra","c":[38.24444,21.73444],"p":"GR"},{"i":"5102466","n":"Paterson","c":[40.91677,-74.17181],"p":"US"},{"i":"3454783","n":"Patos de Minas","c":[-18.57889,-46.51806],"p":"BR"},{"i":"1614295","n":"Pattaya","c":[12.93333,100.88333],"p":"TH"},{"i":"1260173","n":"Patan","c":[23.8507,72.12963],"p":"IN"},{"i":"1631992","n":"Pati","c":[-6.7559,111.038],"p":"ID"},{"i":"3392887","n":"Patos","c":[-7.02444,-37.28],"p":"BR"},{"i":"302819","n":"Patnos","c":[39.22493,42.85693],"p":"TR"},{"i":"3454763","n":"Patrocinio","c":[-18.94389,-46.9925],"p":"BR"},{"i":"1168226","n":"Pattoki","c":[31.02021,73.85333],"p":"PK"},{"i":"1260040","n":"Pattukkottai","c":[10.42358,79.31949],"p":"IN"},{"i":"3454818","n":"Pato Branco","c":[-26.22861,-52.67056],"p":"BR"},{"i":"2512862","n":"Paterna","c":[39.50263,-0.44079],"p":"ES"},{"i":"3591512","n":"Patzun","c":[14.68189,-91.01397],"p":"GT"},{"i":"3993179","n":"Patzcuaro","c":[19.51594,-101.60887],"p":"MX"},{"i":"1694290","n":"Patuto","c":[14.11667,120.96667],"p":"PH"},{"i":"1185148","n":"Patiya","c":[22.29543,91.979],"p":"BD"}]