[{"i":"1818209","n":"Tsuen Wan","c":[22.37137,114.11329],"p":"HK"},{"i":"2110683","n":"Tsukuba","c":[36.2,140.1],"p":"JP"},{"i":"1849796","n":"Tsu","c":[34.73333,136.51667],"p":"JP"},{"i":"1849563","n":"Tsuruoka","c":[38.72167,139.82167],"p":"JP"},{"i":"1849519","n":"Tsuyama","c":[35.05215,133.99885],"p":"JP"},{"i":"1849788","n":"Tsubame","c":[37.6645,138.92518],"p":"JP"},{"i":"1849561","n":"Tsurusaki","c":[33.24528,131.69165],"p":"JP"},{"i":"1849592","n":"Tsuruga","c":[35.653,136.06331],"p":"JP"},{"i":"1849539","n":"Tsushima","c":[35.16667,136.71667],"p":"JP"}]